import java.io.PrintStream;

public class PrintThatNumber { public static void main(Throwable paramThrowable) { paramThrowable.printStackTrace(); }
  public static void main(int paramInt, PrintStream paramPrintStream) { paramPrintStream.println(paramInt); }
  
  static { II1 = new Boolean(true);
    
    SSS = 846;
    
    $5$ = 35;
    
    $SS = 27;
    
    ___ = 2;
    
    S$$ = 4;
    
    ll1 = 21;
    
    lI1 = 87;
  }
  
  int $5S;
  int S$$$;
  int lll;
  public static int lI1;
  public static int ll1;
  public static int S$$;
  public static int III;
  public static int ___;
  public static int $SS;
  public static int $5$;
  public static int SSS;
  public static Boolean II1;
  public static boolean Ill;
  public static void main(String[] paramArrayOfString)
  {
    long l2 = 0L;
    
    long l1 = 0L;
    

    try
    {
      paramArrayOfString = new PrintThatNumber($5$);
      
















      try
      {
        main(PrintThatNumberSSSlll ^ (int)((lll & 0xFFFFFFFF ^ l2 & 0xFFFFFFFF00000000) & 0xFFFFFFFF), System.out);
      } catch (RuntimeException localRuntimeException1) {
        main(localRuntimeException1);
      }
      return; } catch (RuntimeException localRuntimeException2) { main(localRuntimeException2);
    }
  }
  
  /* Error */
  public PrintThatNumber(int arg1)
  {
    // Byte code:
    //   0: lconst_0
    //   1: lstore 11
    //   3: lconst_0
    //   4: lstore 9
    //   6: lconst_0
    //   7: lstore 7
    //   9: lconst_0
    //   10: lstore 5
    //   12: lconst_0
    //   13: lstore_3
    //   14: aload_0
    //   15: invokespecial 94 java/lang/Object:<init> ()V
    //   18: iload_1
    //   19: sipush 262
    //   22: ishl
    //   23: i2l
    //   24: ldc2_w 35
    //   27: land
    //   28: lconst_0
    //   29: ldc2_w 85
    //   32: land
    //   33: lxor
    //   34: iload_1
    //   35: bipush 23
    //   37: imul
    //   38: i2l
    //   39: ldc2_w 35
    //   42: land
    //   43: lconst_0
    //   44: ldc2_w 85
    //   47: land
    //   48: lxor
    //   49: lstore_3
    //   50: ldc2_w 35
    //   53: land
    //   54: l2i
    //   55: lload_3
    //   56: ldc2_w 35
    //   59: land
    //   60: l2i
    //   61: iadd
    //   62: i2l
    //   63: ldc2_w 35
    //   66: land
    //   67: lconst_0
    //   68: ldc2_w 85
    //   71: land
    //   72: lxor
    //   73: ldc2_w 35
    //   76: land
    //   77: l2i
    //   78: getstatic 46 PrintThatNumber:ll1 I
    //   81: iadd
    //   82: i2l
    //   83: ldc2_w 35
    //   86: land
    //   87: lconst_0
    //   88: ldc2_w 85
    //   91: land
    //   92: lxor
    //   93: lstore 9
    //   95: aload_0
    //   96: getstatic 45 PrintThatNumber:II1 Ljava/lang/Boolean;
    //   99: invokevirtual 72 java/lang/Boolean:booleanValue  ()Z
    //   102: ifge +8 -> 110
    //   105: pop
    //   106: goto +146 -> 252
    //   109: athrow
    //   110: lload 9
    //   112: ldc2_w 35
    //   115: land
    //   116: l2i
    //   117: putfield 92 PrintThatNumber:$5S I
    //   120: aload_0
    //   121: iload_1
    //   122: getstatic 48  PrintThatNumber:S$$ I
    //   125: isub
    //   126: putfield 16 PrintThatNumber:S$$$  I
    //   129: getstatic 57  PrintThatNumber:III I
    //   132: istore_2
    //   133: goto +108 -> 241
    //   136: aload_0
    //   137: getfield 90 PrintThatNumber:lll I
    //   140: i2l
    //   141: ldc2_w 35
    //   144: land
    //   145: lload 7
    //   147: ldc2_w 85
    //   150: land
    //   151: lxor
    //   152: lstore 7
    //   154: aload_0
    //   155: getfield 92 PrintThatNumber:$5S I
    //   158: i2l
    //   159: bipush 32
    //   161: lshl
    //   162: ldc2_w 85
    //   165: land
    //   166: lload_3
    //   167: ldc2_w 35
    //   170: land
    //   171: lxor
    //   172: lstore_3
    //   173: iload_1
    //   174: lload_3
    //   175: ldc2_w 85
    //   178: land
    //   179: bipush 32
    //   181: lshr
    //   182: l2i
    //   183: iadd
    //   184: i2l
    //   185: ldc2_w 35
    //   188: land
    //   189: lload 5
    //   191: ldc2_w 85
    //   194: land
    //   195: lxor
    //   196: lstore 5
    //   198: lload 7
    //   200: ldc2_w 35
    //   203: land
    //   204: l2i
    //   205: lload 5
    //   207: ldc2_w 35
    //   210: land
    //   211: l2i
    //   212: iadd
    //   213: i2l
    //   214: ldc2_w 35
    //   217: land
    //   218: lload 11
    //   220: ldc2_w 85
    //   223: land
    //   224: lxor
    //   225: lstore 11
    //   227: aload_0
    //   228: lload 11
    //   230: ldc2_w 35
    //   233: land
    //   234: l2i
    //   235: putfield 90 PrintThatNumber:lll I
    //   238: iinc 2 2
    //   241: iload_2
    //   242: getstatic 1 PrintThatNumber:$SS I
    //   245: if_icmplt +4 -> 249
    //   248: return
    //   249: goto -113 -> 136
    //   252: aconst_null
    //   253: goto -144 -> 109
    //   256: nop
    // Line number table:
    //   Java source line #0  -> byte code offset #0
    //   Java source line #1  -> byte code offset #1
    //   Java source line #2  -> byte code offset #3
    //   Java source line #3  -> byte code offset #4
    //   Java source line #4  -> byte code offset #6
    //   Java source line #5  -> byte code offset #7
    //   Java source line #6  -> byte code offset #9
    //   Java source line #7  -> byte code offset #10
    //   Java source line #8  -> byte code offset #12
    //   Java source line #9  -> byte code offset #13
    //   Java source line #10 -> byte code offset #14
    //   Java source line #11 -> byte code offset #15
    //   Java source line #12 -> byte code offset #18
    //   Java source line #13 -> byte code offset #19
    //   Java source line #14 -> byte code offset #22
    //   Java source line #15 -> byte code offset #23
    //   Java source line #16 -> byte code offset #24
    //   Java source line #17 -> byte code offset #27
    //   Java source line #18 -> byte code offset #28
    //   Java source line #19 -> byte code offset #29
    //   Java source line #20 -> byte code offset #32
    //   Java source line #21 -> byte code offset #33
    //   Java source line #22 -> byte code offset #34
    //   Java source line #23 -> byte code offset #35
    //   Java source line #24 -> byte code offset #37
    //   Java source line #25 -> byte code offset #38
    //   Java source line #26 -> byte code offset #39
    //   Java source line #27 -> byte code offset #42
    //   Java source line #28 -> byte code offset #43
    //   Java source line #29 -> byte code offset #44
    //   Java source line #30 -> byte code offset #47
    //   Java source line #31 -> byte code offset #48
    //   Java source line #32 -> byte code offset #49
    //   Java source line #33 -> byte code offset #50
    //   Java source line #34 -> byte code offset #53
    //   Java source line #35 -> byte code offset #54
    //   Java source line #36 -> byte code offset #55
    //   Java source line #37 -> byte code offset #56
    //   Java source line #38 -> byte code offset #59
    //   Java source line #39 -> byte code offset #60
    //   Java source line #40 -> byte code offset #61
    //   Java source line #41 -> byte code offset #62
    //   Java source line #42 -> byte code offset #63
    //   Java source line #43 -> byte code offset #66
    //   Java source line #44 -> byte code offset #67
    //   Java source line #45 -> byte code offset #68
    //   Java source line #46 -> byte code offset #71
    //   Java source line #47 -> byte code offset #72
    //   Java source line #48 -> byte code offset #73
    //   Java source line #49 -> byte code offset #76
    //   Java source line #50 -> byte code offset #77
    //   Java source line #51 -> byte code offset #78
    //   Java source line #52 -> byte code offset #81
    //   Java source line #53 -> byte code offset #82
    //   Java source line #54 -> byte code offset #83
    //   Java source line #55 -> byte code offset #86
    //   Java source line #56 -> byte code offset #87
    //   Java source line #57 -> byte code offset #88
    //   Java source line #58 -> byte code offset #91
    //   Java source line #59 -> byte code offset #92
    //   Java source line #60 -> byte code offset #93
    //   Java source line #61 -> byte code offset #95
    //   Java source line #62 -> byte code offset #96
    //   Java source line #63 -> byte code offset #99
    //   Java source line #64 -> byte code offset #102
    //   Java source line #65 -> byte code offset #105
    //   Java source line #66 -> byte code offset #106
    //   Java source line #67 -> byte code offset #109
    //   Java source line #68 -> byte code offset #110
    //   Java source line #69 -> byte code offset #112
    //   Java source line #70 -> byte code offset #115
    //   Java source line #71 -> byte code offset #116
    //   Java source line #72 -> byte code offset #117
    //   Java source line #73 -> byte code offset #120
    //   Java source line #74 -> byte code offset #121
    //   Java source line #75 -> byte code offset #122
    //   Java source line #76 -> byte code offset #125
    //   Java source line #77 -> byte code offset #126
    //   Java source line #78 -> byte code offset #129
    //   Java source line #79 -> byte code offset #132
    //   Java source line #80 -> byte code offset #133
    //   Java source line #81 -> byte code offset #136
    //   Java source line #82 -> byte code offset #137
    //   Java source line #83 -> byte code offset #140
    //   Java source line #84 -> byte code offset #141
    //   Java source line #85 -> byte code offset #144
    //   Java source line #86 -> byte code offset #145
    //   Java source line #87 -> byte code offset #147
    //   Java source line #88 -> byte code offset #150
    //   Java source line #89 -> byte code offset #151
    //   Java source line #90 -> byte code offset #152
    //   Java source line #91 -> byte code offset #154
    //   Java source line #92 -> byte code offset #155
    //   Java source line #93 -> byte code offset #158
    //   Java source line #94 -> byte code offset #159
    //   Java source line #95 -> byte code offset #161
    //   Java source line #96 -> byte code offset #162
    //   Java source line #97 -> byte code offset #165
    //   Java source line #98 -> byte code offset #166
    //   Java source line #99 -> byte code offset #167
    //   Java source line #100  -> byte code offset #170
    //   Java source line #101  -> byte code offset #171
    //   Java source line #102  -> byte code offset #172
    //   Java source line #103  -> byte code offset #173
    //   Java source line #104  -> byte code offset #174
    //   Java source line #105  -> byte code offset #175
    //   Java source line #106  -> byte code offset #178
    //   Java source line #107  -> byte code offset #179
    //   Java source line #108  -> byte code offset #181
    //   Java source line #109  -> byte code offset #182
    //   Java source line #110  -> byte code offset #183
    //   Java source line #111  -> byte code offset #184
    //   Java source line #112  -> byte code offset #185
    //   Java source line #113  -> byte code offset #188
    //   Java source line #114  -> byte code offset #189
    //   Java source line #115  -> byte code offset #191
    //   Java source line #116  -> byte code offset #194
    //   Java source line #117  -> byte code offset #195
    //   Java source line #118  -> byte code offset #196
    //   Java source line #119  -> byte code offset #198
    //   Java source line #120  -> byte code offset #200
    //   Java source line #121  -> byte code offset #203
    //   Java source line #122  -> byte code offset #204
    //   Java source line #123  -> byte code offset #205
    //   Java source line #124  -> byte code offset #207
    //   Java source line #125  -> byte code offset #210
    //   Java source line #126  -> byte code offset #211
    //   Java source line #127  -> byte code offset #212
    //   Java source line #128  -> byte code offset #213
    //   Java source line #129  -> byte code offset #214
    //   Java source line #130  -> byte code offset #217
    //   Java source line #131  -> byte code offset #218
    //   Java source line #132  -> byte code offset #220
    //   Java source line #133  -> byte code offset #223
    //   Java source line #134  -> byte code offset #224
    //   Java source line #135  -> byte code offset #225
    //   Java source line #136  -> byte code offset #227
    //   Java source line #137  -> byte code offset #228
    //   Java source line #138  -> byte code offset #230
    //   Java source line #139  -> byte code offset #233
    //   Java source line #140  -> byte code offset #234
    //   Java source line #141  -> byte code offset #235
    //   Java source line #142  -> byte code offset #238
    //   Java source line #143  -> byte code offset #241
    //   Java source line #144  -> byte code offset #242
    //   Java source line #145  -> byte code offset #245
    //   Java source line #146  -> byte code offset #248
    //   Java source line #147  -> byte code offset #249
    //   Java source line #148  -> byte code offset #252
    //   Java source line #149  -> byte code offset #253
    //   Java source line #150  -> byte code offset #256
    // Exception table:
    //   from to  target  type
    //   249  256 109 java/lang/ArrayIndexOutOfBoundsException
  }
}